[
  {
    "number": 51,
    "section": "The Ten Commandments",
    "title": "Question 51: Why is it called the Lord’s Day?",
    "question": "Why is it called the Lord’s Day?",
    "answer": "Because on that day Christ rose from the dead.",
    "verses": [
      "Matthew 28:1",
      "Mark 16:9",
      "Luke 24:1-6",
      "John 20:1"
    ],
    "application": "",
    "prayer": "",
    "coloring_page_image": "",
    "activities": []
  },
  {
    "number": 52,
    "section": "The Ten Commandments",
    "title": "Question 52: How should the Sabbath be kept?",
    "question": "How should the Sabbath be kept?",
    "answer": "In prayer and praise, in hearing and reading God’s Word, and in doing good to our fellow men.",
    "verses": [
      "Isaiah 58:13-14",
      "Acts 20:7",
      "1 Corinthians 16:2",
      "Luke 4:16",
      "Matthew 12:10-13"
    ],
    "application": "",
    "prayer": "",
    "coloring_page_image": "",
    "activities": []
  },
  {
    "number": 53,
    "section": "The Ten Commandments",
    "title": "Question 53: What is the fifth commandment?",
    "question": "What is the fifth commandment?",
    "answer": "The fifth commandment is, 'Honor your father and your mother, that your days may be long in the land that the Lord your God is giving you.'",
    "verses": [
      "Exodus 20:12"
    ],
    "application": "",
    "prayer": "",
    "coloring_page_image": "",
    "activities": []
  },
  {
    "number": 54,
    "section": "The Ten Commandments",
    "title": "Question 54: What does the fifth commandment teach us?",
    "question": "What does the fifth commandment teach us?",
    "answer": "To love and obey our parents.",
    "verses": [
      "Matthew 15:3-6",
      "Ephesians 6:1-3",
      "Colossians 3:20"
    ],
    "application": "",
    "prayer": "",
    "coloring_page_image": "",
    "activities": []
  },
  {
    "number": 55,
    "section": "The Ten Commandments",
    "title": "Question 55: What is the sixth commandment?",
    "question": "What is the sixth commandment?",
    "answer": "The sixth commandment is, 'You shall not murder.'",
    "verses": [
      "Exodus 20:13"
    ],
    "application": "",
    "prayer": "",
    "coloring_page_image": "",
    "activities": []
  },
  {
    "number": 56,
    "section": "The Ten Commandments",
    "title": "Question 56: What does the sixth commandment teach us?",
    "question": "What does the sixth commandment teach us?",
    "answer": "To avoid hatred, all that leads to it, and all that follows from it.",
    "verses": [
      "Matthew 5:21-24",
      "1 John 3:15",
      "James 4:1-3"
    ],
    "application": "",
    "prayer": "",
    "coloring_page_image": "",
    "activities": []
  },
  {
    "number": 57,
    "section": "The Ten Commandments",
    "title": "Question 57: What is the seventh commandment?",
    "question": "What is the seventh commandment?",
    "answer": "The seventh commandment is, 'You shall not commit adultery.'",
    "verses": [
      "Exodus 20:14"
    ],
    "application": "",
    "prayer": "",
    "coloring_page_image": "",
    "activities": []
  },
  {
    "number": 58,
    "section": "The Ten Commandments",
    "title": "Question 58: What does the seventh commandment teach us?",
    "question": "What does the seventh commandment teach us?",
    "answer": "To be pure in heart, language and conduct.",
    "verses": [
      "Matthew 5:27-28",
      "Ephesians 5:3-5",
      "Philippians 4:8-9"
    ],
    "application": "",
    "prayer": "",
    "coloring_page_image": "",
    "activities": []
  },
  {
    "number": 59,
    "section": "The Ten Commandments",
    "title": "Question 59: What is the eighth commandment?",
    "question": "What is the eighth commandment?",
    "answer": "The eighth commandment is, 'You shall not steal.'",
    "verses": [
      "Exodus 20:15"
    ],
    "application": "",
    "prayer": "",
    "coloring_page_image": "",
    "activities": []
  },
  {
    "number": 60,
    "section": "The Ten Commandments",
    "title": "Question 60: What does the eighth commandment teach us?",
    "question": "What does the eighth commandment teach us?",
    "answer": "To be honest and not to take the things of others.",
    "verses": [
      "Exodus 23:4",
      "Proverbs 21:6-7",
      "Ephesians 4:28"
    ],
    "application": "",
    "prayer": "",
    "coloring_page_image": "",
    "activities": []
  },
  {
    "number": 61,
    "section": "The Ten Commandments",
    "title": "Question 61: What is the ninth commandment?",
    "question": "What is the ninth commandment?",
    "answer": "The ninth commandment is, 'You shall not bear false witness against your neighbor.'",
    "verses": [
      "Exodus 20:16"
    ],
    "application": "",
    "prayer": "",
    "coloring_page_image": "",
    "activities": []
  },
  {
    "number": 62,
    "section": "The Ten Commandments",
    "title": "Question 62: What does the ninth commandment teach us?",
    "question": "What does the ninth commandment teach us?",
    "answer": "To tell the truth and not to speak evil of others.",
    "verses": [
      "Psalm 15:1-3",
      "Zechariah 8:16",
      "1 Corinthians 13:6",
      "James 4:11"
    ],
    "application": "",
    "prayer": "",
    "coloring_page_image": "",
    "activities": []
  },
  {
    "number": 63,
    "section": "The Ten Commandments",
    "title": "Question 63: What is the tenth commandment?",
    "question": "What is the tenth commandment?",
    "answer": "The tenth commandment is, 'You shall not covet your neighbor’s house; you shall not covet your neighbor’s wife, or his male servant, or his female servant, or his ox, or his donkey, or anything that is your neighbor’s.'",
    "verses": [
      "Exodus 20:17"
    ],
    "application": "",
    "prayer": "",
    "coloring_page_image": "",
    "activities": []
  },
  {
    "number": 64,
    "section": "The Ten Commandments",
    "title": "Question 64: What does the tenth commandment teach us?",
    "question": "What does the tenth commandment teach us?",
    "answer": "To be content with what we have.",
    "verses": [
      "Philippians 4:11",
      "1 Timothy 6:6-8",
      "Hebrews 13:5"
    ],
    "application": "",
    "prayer": "",
    "coloring_page_image": "",
    "activities": []
  },
  {
    "number": 65,
    "section": "The Ten Commandments",
    "title": "Question 65: Can any man keep these ten commandments?",
    "question": "Can any man keep these ten commandments?",
    "answer": "No mere man, since the fall of Adam, ever did or can keep the ten commandments perfectly.",
    "verses": [
      "Proverbs 20:9",
      "Ecclesiastes 7:20",
      "Romans 3:19-20",
      "James 2:10",
      "1 John 1:8, 10"
    ],
    "application": "",
    "prayer": "",
    "coloring_page_image": "",
    "activities": []
  },
  {
    "number": 66,
    "section": "The Ten Commandments",
    "title": "Question 66: Of what use are the ten commandments to us?",
    "question": "Of what use are the ten commandments to us?",
    "answer": "They teach us our duty, make clear our condemnation, and show us our need of a Saviour.",
    "verses": [
      "1 Timothy 1:8-11",
      "Romans 3:20",
      "Galatians 3:24"
    ],
    "application": "",
    "prayer": "",
    "coloring_page_image": "",
    "activities": []
  },
  {
    "number": 67,
    "section": "The Ten Commandments",
    "title": "Question 67: Does God condemn all men?",
    "question": "Does God condemn all men?",
    "answer": "No. Though he could justly have done so he has graciously entered into a covenant to save many.",
    "verses": [
      "Romans 3:19-20, 23-25",
      "John 17:11-12",
      "Isaiah 53:11"
    ],
    "application": "",
    "prayer": "",
    "coloring_page_image": "",
    "activities": []
  }
]